genomictools.cpython-312-x86_64-linux-gnu.so
genomictools-0.0.8.dist-info/METADATA
genomictools-0.0.8.dist-info/WHEEL
genomictools-0.0.8.dist-info/top_level.txt
genomictools-0.0.8.dist-info/RECORD
